django_quik/__init__.py
django_quik/cli.py
django_quik/config.py
django_quik/loader.py
django_quik/tailwind.py
django_quik/server/__init__.py
django_quik/server/http.py
django_quik-0.0.8.dist-info/METADATA
django_quik-0.0.8.dist-info/WHEEL
django_quik-0.0.8.dist-info/entry_points.txt
django_quik-0.0.8.dist-info/top_level.txt
django_quik-0.0.8.dist-info/RECORD
