Metadata-Version: 2.1
Name: django-quik
Version: 0.0.8
Summary: Powering up your Django experience.
Author-email: Tej Magar <tejmagar20510@gmail.com>
Project-URL: Repository, https://github.com/tejmagar/django-quik
Project-URL: Bug Tracker, https://github.com/tejmagar/django-quik/issues
Requires-Dist: watchdog>=6.0.0
